qlik_test_etay/.idea/inspectionProfiles/profiles_settings.xml
qlik_test_etay/.idea/misc.xml
qlik_test_etay/.idea/modules.xml
qlik_test_etay/.idea/qlik_test_etay.iml
qlik_test_etay/.idea/workspace.xml
qlik_test_etay/__init__.py
qlik_test_etay-0.1.0.dist-info/METADATA
qlik_test_etay-0.1.0.dist-info/WHEEL
qlik_test_etay-0.1.0.dist-info/RECORD
