Metadata-Version: 2.1
Name: qlik-test-etay
Version: 0.1.0
Summary: 
Author: Your Name
Author-email: you@example.com
Requires-Python: >=3.11,<4.0
Classifier: Programming Language :: Python :: 3
Classifier: Programming Language :: Python :: 3.11
Requires-Dist: flask (>=2.2.3,<3.0.0)
Requires-Dist: pandas (>=1.5.3,<2.0.0)
